fft/fft_core.v/input_controller.v
`timescale 1ns/1ps

module input_controller #(
    parameter FFT_SIZE   = 16,
    parameter DATA_WIDTH = 12
)(
    input  wire                  clk,
    input  wire                  rst_n,

    // From FFT buffer
    input  wire                  fft_frame_valid,
    input  wire [DATA_WIDTH-1:0] buffer_data,

    // Control signals to FFT buffer
    output reg                   buffer_read_en,
    output reg [3:0]             buffer_addr,

    // Control signals to FFT core
    output reg                   fft_start,
    output reg                   fft_valid
);

    //------------------------------------------------
    // States
    //------------------------------------------------

    localparam IDLE = 2'd0;
    localparam READ = 2'd1;
    localparam DONE = 2'd2;

    reg [1:0] state;

    //------------------------------------------------
    // State Machine
    //------------------------------------------------

    always @(posedge clk or negedge rst_n)
    begin

        if (!rst_n)
        begin
            state          <= IDLE;
            buffer_addr    <= 4'd0;
            buffer_read_en <= 1'b0;
            fft_start      <= 1'b0;
            fft_valid      <= 1'b0;
        end

        else
        begin

            // Default values
            buffer_read_en <= 1'b0;
            fft_start      <= 1'b0;
            fft_valid      <= 1'b0;

            case (state)

                //------------------------------------
                // WAIT FOR COMPLETE FFT FRAME
                //------------------------------------

                IDLE:
                begin

                    buffer_addr <= 4'd0;

                    if (fft_frame_valid)
                    begin
                        state <= READ;
                    end

                end

                //------------------------------------
                // READ 16 SAMPLES
                //------------------------------------

                READ:
                begin

                    buffer_read_en <= 1'b1;
                    fft_valid      <= 1'b1;

                    //--------------------------------
                    // Last sample
                    //--------------------------------

                    if (buffer_addr == FFT_SIZE-1)
                    begin
                        state <= DONE;
                    end

                    else
                    begin
                        buffer_addr <= buffer_addr + 1'b1;
                    end

                end

                //------------------------------------
                // START FFT
                //------------------------------------

                DONE:
                begin

                    buffer_read_en <= 1'b0;
                    fft_valid      <= 1'b0;

                    // Tell FFT core that all
                    // 16 samples have been read
                    fft_start <= 1'b1;

                    buffer_addr <= 4'd0;

                    state <= IDLE;

                end

                default:
                begin

                    state <= IDLE;

                end

            endcase

        end

    end

endmodule

fft/fft_core.v/input_controller_tb.v
`timescale 1ns/1ps

module input_controller_tb;

    //------------------------------------------------
    // Parameters
    //------------------------------------------------

    parameter FFT_SIZE   = 16;
    parameter DATA_WIDTH = 12;

    //------------------------------------------------
    // DUT Inputs
    //------------------------------------------------

    reg clk;
    reg rst_n;

    reg fft_frame_valid;
    reg [DATA_WIDTH-1:0] buffer_data;

    //------------------------------------------------
    // DUT Outputs
    //------------------------------------------------

    wire buffer_read_en;
    wire [3:0] buffer_addr;
    wire fft_start;
    wire fft_valid;

    //------------------------------------------------
    // Test Buffer
    //------------------------------------------------

    reg [DATA_WIDTH-1:0] test_buffer [0:FFT_SIZE-1];

    integer i;
    integer errors;

    //------------------------------------------------
    // DUT
    //------------------------------------------------

    input_controller #(
        .FFT_SIZE(FFT_SIZE),
        .DATA_WIDTH(DATA_WIDTH)
    ) uut (

        .clk(clk),
        .rst_n(rst_n),

        .fft_frame_valid(fft_frame_valid),
        .buffer_data(buffer_data),

        .buffer_read_en(buffer_read_en),
        .buffer_addr(buffer_addr),

        .fft_start(fft_start),
        .fft_valid(fft_valid)

    );

    //------------------------------------------------
    // 100 MHz Clock
    //------------------------------------------------

    initial
        clk = 1'b0;

    always #5 clk = ~clk;

    //------------------------------------------------
    // Fake FFT Buffer Data
    //------------------------------------------------

    always @(*)
    begin
        buffer_data = test_buffer[buffer_addr];
    end

    //------------------------------------------------
    // Main Test
    //------------------------------------------------

    initial
    begin

        errors = 0;

        fft_frame_valid = 1'b0;

        //------------------------------------------------
        // Fill fake FFT buffer
        //------------------------------------------------

        for (i = 0; i < FFT_SIZE; i = i + 1)
        begin
            test_buffer[i] = 12'd100 + i;
        end

        //------------------------------------------------
        // Reset
        //------------------------------------------------

        rst_n = 1'b0;

        #100;

        rst_n = 1'b1;

        $display("");
        $display("----------------------------------------");
        $display(" INPUT CONTROLLER TEST STARTED");
        $display("----------------------------------------");

        //------------------------------------------------
        // Tell controller that frame is ready
        //------------------------------------------------

        @(posedge clk);

        fft_frame_valid <= 1'b1;

        @(posedge clk);

        fft_frame_valid <= 1'b0;

        //------------------------------------------------
        // Check 16 samples
        //------------------------------------------------

        for (i = 0; i < FFT_SIZE; i = i + 1)
        begin

            @(posedge clk);

            #1;

            //------------------------------------------------
            // Check read enable
            //------------------------------------------------

            if (buffer_read_en !== 1'b1)
            begin

                $display(
                    "ERROR: buffer_read_en not HIGH at address %0d",
                    i
                );

                errors = errors + 1;

            end

            //------------------------------------------------
            // Check address
            //------------------------------------------------

            if (buffer_addr !== i)
            begin

                $display(
                    "ERROR: Address = %0d, Expected = %0d",
                    buffer_addr,
                    i
                );

                errors = errors + 1;

            end

            //------------------------------------------------
            // Check FFT valid
            //------------------------------------------------

            if (fft_valid !== 1'b1)
            begin

                $display(
                    "ERROR: fft_valid not HIGH at address %0d",
                    i
                );

                errors = errors + 1;

            end

            //------------------------------------------------
            // Display successful read
            //------------------------------------------------

            $display(
                "PASS: Address=%0d  Data=%0d  Read_EN=%b  FFT_VALID=%b",
                buffer_addr,
                buffer_data,
                buffer_read_en,
                fft_valid
            );

        end

        //------------------------------------------------
        // Check FFT start
        //------------------------------------------------

        @(posedge clk);

        #1;

        if (fft_start !== 1'b1)
        begin

            $display("ERROR: fft_start was not asserted!");

            errors = errors + 1;

        end

        else
        begin

            $display("");
            $display("PASS: fft_start asserted");
        end

        //------------------------------------------------
        // Final result
        //------------------------------------------------

        #20;

        $display("");
        $display("========================================");

        if (errors == 0)
        begin

            $display(" INPUT CONTROLLER TEST PASSED");
            $display(" NO ERRORS");

        end

        else
        begin

            $display(" INPUT CONTROLLER TEST FAILED");
            $display(" ERRORS = %0d", errors);

        end

        $display("========================================");
        $display("");

        $finish;

    end

    //------------------------------------------------
    // Waveform
    //------------------------------------------------

    initial
    begin

        $dumpfile("input_controller.vcd");
        $dumpvars(0, input_controller_tb);

    end

endmodule

fft/fft_core.v/input_controller.vcd
$date
	Mon Aug 10 16:17:08 2026
$end
$version
	Icarus Verilog
$end
$timescale
	1ps
$end
$scope module input_controller_tb $end
$var wire 1 ! fft_valid $end
$var wire 1 " fft_start $end
$var wire 1 # buffer_read_en $end
$var wire 4 $ buffer_addr [3:0] $end
$var reg 12 % buffer_data [11:0] $end
$var reg 1 & clk $end
$var reg 1 ' fft_frame_valid $end
$var reg 1 ( rst_n $end
$var integer 32 ) errors [31:0] $end
$var integer 32 * i [31:0] $end
$scope module uut $end
$var wire 12 + buffer_data [11:0] $end
$var wire 1 & clk $end
$var wire 1 ' fft_frame_valid $end
$var wire 1 ( rst_n $end
$var reg 4 , buffer_addr [3:0] $end
$var reg 1 # buffer_read_en $end
$var reg 1 " fft_start $end
$var reg 1 ! fft_valid $end
$var reg 2 - state [1:0] $end
$upscope $end
$upscope $end
$enddefinitions $end
#0
$dumpvars
b0 -
b0 ,
b1100100 +
b10000 *
b0 )
0(
0'
0&
b1100100 %
b0 $
0#
0"
0!
$end
#5000
1&
#10000
0&
#15000
1&
#20000
0&
#25000
1&
#30000
0&
#35000
1&
#40000
0&
#45000
1&
#50000
0&
#55000
1&
#60000
0&
#65000
1&
#70000
0&
#75000
1&
#80000
0&
#85000
1&
#90000
0&
#95000
1&
#100000
0&
1(
#105000
1'
1&
#110000
0&
#115000
b1 -
0'
b0 *
1&
#120000
0&
#125000
b1100101 %
b1100101 +
b1 $
b1 ,
1!
1#
1&
#126000
b1 *
b1 )
#130000
0&
#135000
b1100110 %
b1100110 +
b10 $
b10 ,
1!
1#
1&
#136000
b10 *
b10 )
#140000
0&
#145000
b1100111 %
b1100111 +
b11 $
b11 ,
1!
1#
1&
#146000
b11 *
b11 )
#150000
0&
#155000
b1101000 %
b1101000 +
b100 $
b100 ,
1!
1#
1&
#156000
b100 *
b100 )
#160000
0&
#165000
b1101001 %
b1101001 +
b101 $
b101 ,
1!
1#
1&
#166000
b101 *
b101 )
#170000
0&
#175000
b1101010 %
b1101010 +
b110 $
b110 ,
1!
1#
1&
#176000
b110 *
b110 )
#180000
0&
#185000
b1101011 %
b1101011 +
b111 $
b111 ,
1!
1#
1&
#186000
b111 *
b111 )
#190000
0&
#195000
b1101100 %
b1101100 +
b1000 $
b1000 ,
1!
1#
1&
#196000
b1000 *
b1000 )
#200000
0&
#205000
b1101101 %
b1101101 +
b1001 $
b1001 ,
1!
1#
1&
#206000
b1001 *
b1001 )
#210000
0&
#215000
b1101110 %
b1101110 +
b1010 $
b1010 ,
1!
1#
1&
#216000
b1010 *
b1010 )
#220000
0&
#225000
b1101111 %
b1101111 +
b1011 $
b1011 ,
1!
1#
1&
#226000
b1011 *
b1011 )
#230000
0&
#235000
b1110000 %
b1110000 +
b1100 $
b1100 ,
1!
1#
1&
#236000
b1100 *
b1100 )
#240000
0&
#245000
b1110001 %
b1110001 +
b1101 $
b1101 ,
1!
1#
1&
#246000
b1101 *
b1101 )
#250000
0&
#255000
b1110010 %
b1110010 +
b1110 $
b1110 ,
1!
1#
1&
#256000
b1110 *
b1110 )
#260000
0&
#265000
b1110011 %
b1110011 +
b1111 $
b1111 ,
1!
1#
1&
#266000
b1111 *
b1111 )
#270000
0&
#275000
b10 -
1!
1#
1&
#276000
b10000 *
#280000
0&
#285000
b1100100 %
b1100100 +
b0 -
b0 $
b0 ,
1"
0!
0#
1&
#290000
0&
#295000
0"
1&
